{
    "bsonType": "object",
    "properties": {
        "_id": {
            "bsonType": "string"
        },
        "activity": {
            "bsonType": "array",
            "items": {
                "bsonType": "object",
                "properties": {
                    "date": {
                        "bsonType": "string"
                    },
                    "image": {
                        "bsonType": "object",
                        "properties": {
                            "_id": {
                                "bsonType": "string"
                            },
                            "date": {
                                "bsonType": "date"
                            },
                            "picture": {
                                "bsonType": "binData"
                            },
                            "thumbNail": {
                                "bsonType": "binData"
                            }
                        },
                        "required": [
                            "_id",
                            "date"
                        ],
                        "title": "Photo"
                    },
                    "info": {
                        "bsonType": "string"
                    },
                    "type": {
                        "bsonType": "string"
                    },
                    "userAvatar": {
                        "bsonType": "object",
                        "properties": {
                            "_id": {
                                "bsonType": "string"
                            },
                            "date": {
                                "bsonType": "date"
                            },
                            "picture": {
                                "bsonType": "binData"
                            },
                            "thumbNail": {
                                "bsonType": "binData"
                            }
                        },
                        "required": [
                            "_id",
                            "date"
                        ],
                        "title": "Photo"
                    }
                },
                "required": [
                    "type"
                ],
                "title": "Event",
                "userAvatar": {
                    "bsonType": "object",
                    "properties": {
                        "_id": {
                            "bsonType": "string"
                        },
                        "date": {
                            "bsonType": "date"
                        },
                        "picture": {
                            "bsonType": "binData"
                        },
                        "thumbNail": {
                            "bsonType": "binData"
                        }
                    },
                    "required": [
                        "_id",
                        "date"
                    ],
                    "title": "Photo"
                }
            }
        },
        "address": {
            "bsonType": "object",
            "properties": {
                "city": {
                    "bsonType": "string"
                },
                "country": {
                    "bsonType": "string"
                },
                "gateCode": {
                    "bsonType": "string"
                },
                "state": {
                    "bsonType": "string"
                },
                "street": {
                    "bsonType": "string"
                },
                "zip": {
                    "bsonType": "string"
                }
            },
            "required": [],
            "title": "Address"
        },
        "category": {
            "bsonType": "string"
        },
        "email": {
            "bsonType": "string"
        },
        "firstName": {
            "bsonType": "string"
        },
        "jobs": {
            "bsonType": "array",
            "items": {
                "bsonType": "object",
                "properties": {
                    "_id": {
                        "bsonType": "string"
                    },
                    "assignedCrew": {
                        "bsonType": "object",
                        "properties": {
                            "members": {
                                "bsonType": "array",
                                "items": {
                                    "bsonType": "string"
                                }
                            },
                            "name": {
                                "bsonType": "string"
                            }
                        },
                        "required": [],
                        "title": "Crew"
                    },
                    "comments": {
                        "bsonType": "array",
                        "items": {
                            "bsonType": "object",
                            "properties": {
                                "image": {
                                    "bsonType": "object",
                                    "properties": {
                                        "_id": {
                                            "bsonType": "string"
                                        },
                                        "date": {
                                            "bsonType": "date"
                                        },
                                        "picture": {
                                            "bsonType": "binData"
                                        },
                                        "thumbNail": {
                                            "bsonType": "binData"
                                        }
                                    },
                                    "required": [
                                        "_id",
                                        "date"
                                    ],
                                    "title": "Photo"
                                },
                                "message": {
                                    "bsonType": "string"
                                },
                                "postDate": {
                                    "bsonType": "string"
                                },
                                "user": {
                                    "bsonType": "string"
                                }
                            },
                            "required": [],
                            "title": "Comment"
                        }
                    },
                    "completionDate": {
                        "bsonType": "date"
                    },
                    "estimatedTimeToComplete": {
                        "bsonType": "long"
                    },
                    "isActive": {
                        "bsonType": "string"
                    },
                    "materials": {
                        "bsonType": "array",
                        "items": {
                            "bsonType": "object",
                            "properties": {
                                "SKU": {
                                    "bsonType": "string"
                                },
                                "color": {
                                    "bsonType": "string"
                                },
                                "itemDescription": {
                                    "bsonType": "string"
                                },
                                "photo": {
                                    "bsonType": "object",
                                    "properties": {
                                        "_id": {
                                            "bsonType": "string"
                                        },
                                        "date": {
                                            "bsonType": "date"
                                        },
                                        "picture": {
                                            "bsonType": "binData"
                                        },
                                        "thumbNail": {
                                            "bsonType": "binData"
                                        }
                                    },
                                    "required": [
                                        "_id",
                                        "date"
                                    ],
                                    "title": "Photo"
                                },
                                "price": {
                                    "bsonType": "double"
                                },
                                "quantity": {
                                    "bsonType": "double"
                                },
                                "type": {
                                    "bsonType": "string"
                                }
                            },
                            "required": [],
                            "title": "Material"
                        }
                    },
                    "startDate": {
                        "bsonType": "date"
                    },
                    "startTime": {
                        "bsonType": "date"
                    }
                },
                "required": [
                    "_id"
                ],
                "title": "Job"
            }
        },
        "lastName": {
            "bsonType": "string"
        },
        "partition": {
            "bsonType": "string"
        },
        "phoneNumber": {
            "bsonType": "string"
        }
    },
    "required": [
        "_id",
        "partition",
        "firstName",
        "lastName",
        "email",
        "phoneNumber",
        "category"
    ],
    "title": "Client"
}
